Workbook

Sheet Resumen
C2: Facturación: | D2: =IF(Detalle!F2="",Detalle!E2,Detalle!F2) -> Stocka | E2: 46174
C4: Servicio | D4: Envíos
C5: Servicio Enviame Connect | D5: =COUNTIF(Detalle!I:I,"Servicio Enviame Connect") -> 0 | E5: =SUMIF(Detalle!I:I,"Servicio Enviame Connect",Detalle!V:V) -> 0
C6: Servicio Enviame Connect Plus | D6: =COUNTIF(Detalle!I:I,"Servicio Enviame Connect Plus") -> 0 | E6: =SUMIF(Detalle!I:I,"Servicio Enviame Connect Plus",Detalle!V:V) -> 0
C7: Servicio Enviame Distribucion | D7: =COUNTIF(Detalle!I:I,"Servicio Enviame Distribucion") -> 1349 | E7: =SUMIF(Detalle!I:I,"Servicio Enviame Distribucion",Detalle!V:V) -> 7182156
C8: Servicio Enviame Enviatrack | D8: =COUNTIF(Detalle!I:I,"Servicio Enviame Enviatrack") -> 0 | E8: =SUMIF(Detalle!I:I,"Servicio Enviame Enviatrack",Detalle!V:V) -> 0
C9: Servicio Enviame Flex | D9: =COUNTIF(Detalle!I:I,"Servicio Enviame Flex") -> 0 | E9: =SUMIF(Detalle!I:I,"Servicio Enviame Flex",Detalle!V:V) -> 0
C10: Servicio Enviame Marketcenter | D10: =COUNTIF(Detalle!I:I,"Servicio Enviame Marketcenter") -> 0 | E10: =SUMIF(Detalle!I:I,"Servicio Enviame Marketcenter",Detalle!V:V) -> 0
C11: Servicio Enviame Notificaciones | D11: =COUNTIF(Detalle!I:I,"Servicio Enviame Notificaciones") -> 0 | E11: =SUMIF(Detalle!I:I,"Servicio Enviame Notificaciones",Detalle!V:V) -> 0
C12: Servicio Enviame por Pagar | D12: =COUNTIF(Detalle!I:I,"Servicio Enviame por Pagar") -> 0 | E12: =SUMIF(Detalle!I:I,"Servicio Enviame por Pagar",Detalle!V:V) -> 0
C13: Servicio Enviame Retiros | D13: =COUNTIF(Detalle!I:I,"Servicio Enviame Retiros") -> 0 | E13: =SUMIF(Detalle!I:I,"Servicio Enviame Retiros",Detalle!V:V) -> 0
C14: Servicio Enviame Soporte Tecnico | D14: =COUNTIF(Detalle!I:I,"Servicio Enviame Soporte Tecnico") -> 0 | E14: =SUMIF(Detalle!I:I,"Servicio Enviame Soporte Tecnico",Detalle!V:V) -> 0
C15: Servicio Enviame Modelo Cross Dock | D15: =COUNTIF(Detalle!I:I,"Servicio Enviame Modelo Cross Dock") -> 0 | E15: =SUMIF(Detalle!I:I,"Servicio Enviame Modelo Cross Dock",Detalle!V:V) -> 0
C16: Servicio Enviame Adicional | D16: =COUNTIF(Detalle!I:I,"Servicio Enviame Adicional") -> 0 | E16: =SUMIF(Detalle!I:I,"Servicio Enviame Adicional",Detalle!V:V) -> 0
C17: Servicio Enviame Marketplace | D17: =COUNTIF(Detalle!I:I,"Servicio Enviame Marketplace") -> 1 | E17: =SUMIF(Detalle!I:I,"Servicio Enviame Marketplace",Detalle!V:V) -> 146300
C18: Servicio Enviame Logistica Inversa | D18: =COUNTIF(Detalle!I:I,"Servicio Enviame Logistica Inversa ") -> 0 | E18: =SUMIF(Detalle!I:I,"Servicio Enviame Logistica Inversa ",Detalle!V:V) -> 0
C20: Subtotal | E20: =SUM(E5:E19) -> 7328456
C22: IVA | E22: =E20*0.19 -> 1392406.6
C23: Total | E23: =+E20+E22 -> 8720862.6

Sheet Detalle
A1: company_id | B1: id | C1: imported_id | D1: tracking_number | E1: company | F1: mkp | G1: carrier | H1: carrier_code | I1: contract_type | J1: carrier_service_name | K1: status | L1: comment | M1: name_person | N1: dir_origen | O1: com_origen | P1: dir_destino | Q1: com_destino | R1: created_at | S1: peso informado por carrier | T1: precio | U1: seguro | V1: total
A2: 79452 | B2: 456909122 | C2: BIT11045828 | D2: 272756024 | E2: BACK IN TIME | F2: Stocka | G2: STARKEN | H2: SKN | I2: Servicio Enviame Distribucion | J2: Normal | K2: Entregado | L2: NOMBRE RETIRA: JUAN PARRA . RUT RETIRA: 10599384-6 | M2: Alvaro Leal Godoy | N2: Av. Campos de Deportes 405 | O2: Ñuñoa | P2: Lagos 640, Oficina coopeuch horario de oficina | Q2: Victoria | R2: 2026-06-20 11:02 | S2: 1.1 | T2: 3935 | U2: 0 | V2: 3935
A3: 79452 | B3: 457023449 | C3: BIT11045924 | D3: 272901341 | E3: BACK IN TIME | F3: Stocka | G3: STARKEN | H3: SKN | I3: Servicio Enviame Distribucion | J3: Normal | K3: Entregado | L3: NOMBRE RETIRA: HAROLD TAPIA -- RUT RETIRA: 8258309-2 | M3: Harold Tapia | N3: Av. Campos de Deportes 405 | O3: Ñuñoa | P3: Barrio Las Torcazas, Calle Los Condores 1978 La Serena | Q3: La Serena | R3: 2026-06-24 11:03 | S3: 1 | T3: 3653 | U3: 0 | V3: 3653
A4: 79452 | B4: 456988361 | C4: BIT11045880 | D4: 272827715 | E4: BACK IN TIME | F4: Stocka | G4: STARKEN | H4: SKN | I4: Servicio Enviame Distribucion | J4: Normal | K4: Entregado | L4: NOMBRE RETIRA: CAROLINA GALLEGOA GALLESGOS RUT RETIRA: 22200278-8 | M4: Carolina Gallegos maluenda | N4: Av. Campos de Deportes 405 | O4: Ñuñoa | P4: Francisco De Aguirre 1, Casa 3, 3 | Q4: Copiapó | R4: 2026-06-23 10:44 | S4: 1.1 | T4: 3935 | U4: 0 | V4: 3935
A5: 79452 | B5: 457012762 | C5: BIT11045908 | D5: 272901441 | E5: BACK IN TIME | F5: Stocka | G5: STARKEN | H5: SKN | I5: Servicio Enviame Distribucion | J5: Normal | K5: Entregado | L5: NOMBRE RETIRA: GUILLERMO LEON L RUT RETIRA: 11451476-4 | M5: Guillermo Leon Calleia | N5: Av. Campos de Deportes 405 | O5: Ñuñoa | P5: Zenón Herrera 3525, Departamento 4B | Q5: Chiguayante | R5: 2026-06-23 23:38 | S5: 1.3 | T5: 3631 | U5: 0 | V5: 3631
A6: 79452 | B6: 457023442 | C6: BIT11045921 | D6: 272901364 | E6: BACK IN TIME | F6: Stocka | G6: STARKEN | H6: SKN | I6: Servicio Enviame Distribucion | J6: Normal | K6: Entregado | L6: NOMBRE RETIRA: MAGDALENA CATALAN . RUT RETIRA: 11100298-3 | M6: Ana María Fuentes Valdes | N6: Av. Campos de Deportes 405 | O6: Ñuñoa | P6: Ernesto Pinto Lagarrigue, 2973 | Q6: San Pedro de la Paz | R6: 2026-06-24 11:03 | S6: 1.4 | T6: 3631 | U6: 0 | V6: 3631
A7: 79452 | B7: 456988365 | C7: BIT11045884 | D7: 272827684 | E7: BACK IN TIME | F7: Stocka | G7: STARKEN | H7: SKN | I7: Servicio Enviame Distribucion | J7: Normal | K7: Entregado | L7: NOMBRE RETIRA: DANTE AVILES A RUT RETIRA: 53301990-0 | M7: Mauricio Viñambres | N7: Av. Campos de Deportes 405 | O7: Ñuñoa | P7: De veer 1369, 301 | Q7: Quilpué | R7: 2026-06-23 10:44 | S7: 1.3 | T7: 3250 | U7: 0 | V7: 3250
A8: 79452 | B8: 456988347 | C8: BIT11045871 | D8: 272827730 | E8: BACK IN TIME | F8: Stocka | G8: STARKEN | H8: SKN | I8: Servicio Enviame Distribucion | J8: Normal | K8: Entregado | L8: NOMBRE RETIRA: ANDRES GALLARDO .. RUT RETIRA: 11111111-1 | M8: ANDRES GALLARDO DONOSO | N8: Av. Campos de Deportes 405 | O8: Ñuñoa | P8: AV PANORAMICA 1204, VILLA LA FLORIDA, CASA ESQUINA | Q8: La Serena | R8: 2026-06-23 10:44 | S8: 1.1 | T8: 3653 | U8: 0 | V8: 3653
A9: 79452 | B9: 456988384 | C9: BIT11045893 | D9: 272827637 | E9: BACK IN TIME | F9: Stocka | G9: STARKEN | H9: SKN | I9: Servicio Enviame Distribucion | J9: Normal | K9: Entregado | L9: NOMBRE RETIRA: ANTONIO ARREDONDO . RUT RETIRA: 53333549-7 | M9: Gerardo Blanco | N9: Av. Campos de Deportes 405 | O9: Ñuñoa | P9: Avenida Edmundo Eluchans 2305, Depto 1110, Depto 1110 | Q9: Viña del Mar | R9: 2026-06-23 10:45 | S9: 2.8 | T9: 3250 | U9: 0 | V9: 3250
A10: 79452 | B10: 456703369 | C10: BIT11045700 | D10: 272345713 | E10: BACK IN TIME | F10: Stocka | G10: STARKEN | H10: SKN | I10: Servicio Enviame Distribucion | J10: Normal | K10: Entregado | L10: NOMBRE RETIRA: MARTA PELLE M RUT RETIRA: 11250964-K | M10: Marta Pelle | N10: Av. Campos de Deportes 405 | O10: Ñuñoa | P10: Valle simson 227, Casa | Q10: Coyhaique | R10: 2026-06-14 20:01 | S10: 1.2 | T10: 5564 | U10: 0 | V10: 5564
A11: 79452 | B11: 456933543 | C11: BIT11045846 | D11: 272755954 | E11: BACK IN TIME | F11: Stocka | G11: STARKEN | H11: SKN | I11: Servicio Enviame Distribucion | J11: Normal | K11: Entregado | L11: NOMBRE RETIRA: VICTOR GARRIDO . RUT RETIRA: 9755072-7 | M11: Víctor Garrido López | N11: Av. Campos de Deportes 405 | O11: Ñuñoa | P11: Freiré 673 | Q11: Lebu | R11: 2026-06-21 21:38 | S11: 0.9 | T11: 3631 | U11: 0 | V11: 3631
A12: 79452 | B12: 456909120 | C12: BIT11045823 | D12: 272756054 | E12: BACK IN TIME | F12: Stocka | G12: STARKEN | H12: SKN | I12: Servicio Enviame Distribucion | J12: Normal | K12: Entregado | L12: NOMBRE RETIRA: SILVIA OLLARCE N RUT RETIRA: 53323962-5 | M12: PATRICIO ENRIQUE SANHUEZA BECAR | N12: Av. Campos de Deportes 405 | O12: Ñuñoa | P12: MANUEL RODRIGUEZ 1180, Depto 607 | Q12: Concepción | R12: 2026-06-20 11:02 | S12: 1 | T12: 3631 | U12: 0 | V12: 3631
A13: 79452 | B13: 456933553 | C13: BIT11045854 | D13: 272755898 | E13: BACK IN TIME | F13: Stocka | G13: STARKEN | H13: SKN | I13: Servicio Enviame Distribucion | J13: Normal | K13: Entregado | L13: NOMBRE RETIRA: JUAN BUGUENO J RUT RETIRA: 9311816-2 | M13: Marcela Daian | N13: Av. Campos de Deportes 405 | O13: Ñuñoa | P13: Volcan dona ines 700, Condominio nueva colina casa 66 | Q13: Copiapó | R13: 2026-06-21 21:38 | S13: 1 | T13: 3935 | U13: 0 | V13: 3935
... A1350: 198243 | B1350: 455450616 | C1350: TSS1025 | D1350: 271195463 | E1350: THE SKIN STORE | F1350: Stocka | G1350: STARKEN | H1350: SKN | I1350: Servicio Enviame Distribucion | J1350: Normal | K1350: Entregado | L1350: NOMBRE RETIRA: CAMILA CORNEJO . RUT RETIRA: 18577969-6 | M1350: Aldo Vivaldi | N1350: Av. Campos de Deportes 405 | O1350: Ñuñoa | P1350: Antonio Varas 216, 216 | Q1350: Puerto Montt | R1350: 2026-05-30 13:14 | S1350: 1.4 | T1350: 4205 | U1350: 0 | V1350: 4205
A1351: 0 | F1351: Stocka | I1351: Servicio Enviame Marketplace | S1351: 18 | T1351: 146300 | U1351: 0 | V1351: 146300
